setup.py
panjing.egg-info/PKG-INFO
panjing.egg-info/SOURCES.txt
panjing.egg-info/dependency_links.txt
panjing.egg-info/top_level.txt
panjing/core/__init__.py
panjing/core/short_id.py