Metadata-Version: 1.0
Name: panjing
Version: 2.3
Summary: panjing core
Home-page: https://github.com/newpanjing
Author: panjing
Author-email: newpanjing@icloud.com
License: Apache Licene 2.0
Platform: any
